py_presi/__init__.py
py_presi/__main__.py
py_presi/build.py
py_presi-1.1.6.dist-info/LICENSE
py_presi-1.1.6.dist-info/METADATA
py_presi-1.1.6.dist-info/WHEEL
py_presi-1.1.6.dist-info/entry_points.txt
py_presi-1.1.6.dist-info/top_level.txt
py_presi-1.1.6.dist-info/zip-safe
py_presi-1.1.6.dist-info/RECORD
