Metadata-Version: 2.1
Name: py-presi
Version: 1.1.6
Summary: UNKNOWN
Home-page: UNKNOWN
License: UNKNOWN
Platform: UNKNOWN
Requires-Dist: attrs (==19.3.0)
Requires-Dist: click (==7.1.1)
Requires-Dist: coverage (==5.0.3)
Requires-Dist: darkslide (==5.1.0)
Requires-Dist: docutils (==0.16)
Requires-Dist: entrypoints (==0.3)
Requires-Dist: flake8 (==3.7.9)
Requires-Dist: importlib-metadata (==1.5.0)
Requires-Dist: jinja2 (==2.11.1)
Requires-Dist: markdown (==3.2.1)
Requires-Dist: markupsafe (==1.1.1)
Requires-Dist: mccabe (==0.6.1)
Requires-Dist: more-itertools (==8.2.0)
Requires-Dist: packaging (==20.3)
Requires-Dist: pluggy (==0.13.1)
Requires-Dist: py (==1.8.1)
Requires-Dist: pycodestyle (==2.5.0)
Requires-Dist: pyflakes (==2.1.1)
Requires-Dist: pygments (==2.6.1)
Requires-Dist: pyparsing (==2.4.6)
Requires-Dist: pytest-cov (==2.8.1)
Requires-Dist: pytest (==5.3.5)
Requires-Dist: qrcode (==6.1)
Requires-Dist: six (==1.14.0)
Requires-Dist: wcwidth (==0.1.8)
Requires-Dist: zipp (==3.1.0)
